mypkg1/__init__.py
mypkg1/main.py
mypkg1-0.4.0.dist-info/METADATA
mypkg1-0.4.0.dist-info/WHEEL
mypkg1-0.4.0.dist-info/top_level.txt
mypkg1-0.4.0.dist-info/RECORD
